code/__init__.py
code/main.py
tim_odoo-0.3.0.dist-info/LICENSE
tim_odoo-0.3.0.dist-info/METADATA
tim_odoo-0.3.0.dist-info/WHEEL
tim_odoo-0.3.0.dist-info/top_level.txt
tim_odoo-0.3.0.dist-info/RECORD
