Metadata-Version: 2.1
Name: tim_odoo
Version: 0.3.0
Summary: API func for Odoo
Home-page: https://github.com/OrcCyber/tim.git
Author: Bùi Đức Tuấn
Author-email: buiductuan12081995@gmail.com
Requires-Python: >=3.10
License-File: LICENSE
Requires-Dist: setuptools
Requires-Dist: wheel
